analyze.py
data/__init__.py
data/data_loader.py
data/generate_vectors/__init__.py
data/generate_vectors/bam2tensor.py
data/generate_vectors/create_data.py
main/__init__.py
main/evaluate_sample.py
main/mi_msi_train_test.py
model/__init__.py
model/mi_msi_model.py
model/mi_msi_v0_4_0_200x_attn.model
utils/__init__.py
MiMSI-0.4.1.dist-info/LICENSE
MiMSI-0.4.1.dist-info/METADATA
MiMSI-0.4.1.dist-info/WHEEL
MiMSI-0.4.1.dist-info/entry_points.txt
MiMSI-0.4.1.dist-info/top_level.txt
MiMSI-0.4.1.dist-info/RECORD
