Metadata-Version: 2.1
Name: MiMSI
Version: 0.4.1
Summary: A deep, multiple instance learning based classifier for identifying Microsatellite Instability from NGS
Home-page: https://github.com/mskcc/mimsi
Author: John Ziegler
Author-email: zieglerj@mskcc.org
License: GNU General Public License v3.0
Platform: UNKNOWN
Classifier: Topic :: Scientific/Engineering :: Bio-Informatics
Classifier: Programming Language :: Python :: 2.7
Requires-Python: >=2.7
Requires-Dist: future (==0.18.2)
Requires-Dist: nose (>=1.3.7)
Requires-Dist: numpy (==1.16.1)
Requires-Dist: pandas
Requires-Dist: Pillow
Requires-Dist: pysam (==0.16.0.1)
Requires-Dist: python-dateutil (==2.8.1)
Requires-Dist: scikit-learn
Requires-Dist: scipy
Requires-Dist: six (==1.11.0)
Requires-Dist: sklearn
Requires-Dist: torch (==1.4.0)
Requires-Dist: torchvision (==0.5.0)
Requires-Dist: pandas (==0.24.2) ; python_version <= "2.7"
Requires-Dist: scikit-learn (>=0.20.0) ; python_version <= "2.7"
Requires-Dist: scipy (>=1.1.0) ; python_version <= "2.7"
Requires-Dist: sklearn (==0.0) ; python_version <= "2.7"
